[
    {
        "colo": "Default",
        "ip": "2606:4700:9ad8:1e93:142f:7221:98d2:64ca",
        "latency": 3,
        "line": "CM",
        "loss": 0,
        "node": "NETCUP",
        "speed": 607,
        "time": "2025-06-27 17:27:01"
    },
    {
        "colo": "Default",
        "ip": "2606:4700:9c66:1bf5:8f4:214c:d5a8:9e5a",
        "latency": 4,
        "line": "CM",
        "loss": 0,
        "node": "NETCUP",
        "speed": 545,
        "time": "2025-06-27 17:27:00"
    },
    {
        "colo": "Default",
        "ip": "2606:4700:3027:2c45:93f1:86f3:4e31:9cbe",
        "latency": 13,
        "line": "CM",
        "loss": 0,
        "node": "NETCUP",
        "speed": 438,
        "time": "2025-06-27 17:27:01"
    },
    {
        "colo": "Default",
        "ip": "2606:4700:13b:d5bb:4243:2d47:1ea8:f2a",
        "latency": 4,
        "line": "CM",
        "loss": 0,
        "node": "NETCUP",
        "speed": 433,
        "time": "2025-06-27 17:27:00"
    },
    {
        "colo": "Default",
        "ip": "2606:4700:3027:98ad:70b3:f25b:57e3:8c7b",
        "latency": 4,
        "line": "CM",
        "loss": 0,
        "node": "NETCUP",
        "speed": 424,
        "time": "2025-06-27 17:27:01"
    },
    {
        "colo": "Default",
        "ip": "2606:4700:9ad8:1e93:142f:7221:98d2:64ca",
        "latency": 3,
        "line": "CT",
        "loss": 0,
        "node": "NETCUP",
        "speed": 607,
        "time": "2025-06-27 17:27:01"
    },
    {
        "colo": "Default",
        "ip": "2606:4700:9c66:1bf5:8f4:214c:d5a8:9e5a",
        "latency": 4,
        "line": "CT",
        "loss": 0,
        "node": "NETCUP",
        "speed": 545,
        "time": "2025-06-27 17:27:00"
    },
    {
        "colo": "Default",
        "ip": "2606:4700:3027:2c45:93f1:86f3:4e31:9cbe",
        "latency": 13,
        "line": "CT",
        "loss": 0,
        "node": "NETCUP",
        "speed": 438,
        "time": "2025-06-27 17:27:01"
    },
    {
        "colo": "Default",
        "ip": "2606:4700:13b:d5bb:4243:2d47:1ea8:f2a",
        "latency": 4,
        "line": "CT",
        "loss": 0,
        "node": "NETCUP",
        "speed": 433,
        "time": "2025-06-27 17:27:00"
    },
    {
        "colo": "Default",
        "ip": "2606:4700:3027:98ad:70b3:f25b:57e3:8c7b",
        "latency": 4,
        "line": "CT",
        "loss": 0,
        "node": "NETCUP",
        "speed": 424,
        "time": "2025-06-27 17:27:01"
    },
    {
        "colo": "Default",
        "ip": "2606:4700:9ad8:1e93:142f:7221:98d2:64ca",
        "latency": 3,
        "line": "CU",
        "loss": 0,
        "node": "NETCUP",
        "speed": 607,
        "time": "2025-06-27 17:27:01"
    },
    {
        "colo": "Default",
        "ip": "2606:4700:9c66:1bf5:8f4:214c:d5a8:9e5a",
        "latency": 4,
        "line": "CU",
        "loss": 0,
        "node": "NETCUP",
        "speed": 545,
        "time": "2025-06-27 17:27:00"
    },
    {
        "colo": "Default",
        "ip": "2606:4700:3027:2c45:93f1:86f3:4e31:9cbe",
        "latency": 13,
        "line": "CU",
        "loss": 0,
        "node": "NETCUP",
        "speed": 438,
        "time": "2025-06-27 17:27:01"
    },
    {
        "colo": "Default",
        "ip": "2606:4700:13b:d5bb:4243:2d47:1ea8:f2a",
        "latency": 4,
        "line": "CU",
        "loss": 0,
        "node": "NETCUP",
        "speed": 433,
        "time": "2025-06-27 17:27:00"
    },
    {
        "colo": "Default",
        "ip": "2606:4700:3027:98ad:70b3:f25b:57e3:8c7b",
        "latency": 4,
        "line": "CU",
        "loss": 0,
        "node": "NETCUP",
        "speed": 424,
        "time": "2025-06-27 17:27:01"
    }
]