[
    {
        "colo": "Default",
        "ip": "2606:4700:9ae3:200b:6ae5:e731:51ed:8a43",
        "latency": 4,
        "line": "CM",
        "loss": 0,
        "node": "NETCUP",
        "speed": 518,
        "time": "2025-07-27 15:39:49"
    },
    {
        "colo": "Default",
        "ip": "2606:4700:8ca7:b732:f7ba:4b48:c63b:861a",
        "latency": 4,
        "line": "CM",
        "loss": 0,
        "node": "NETCUP",
        "speed": 492,
        "time": "2025-07-27 15:39:49"
    },
    {
        "colo": "Default",
        "ip": "2606:4700:99eb:f783:fcd5:1bf0:fa5d:e757",
        "latency": 3,
        "line": "CM",
        "loss": 0,
        "node": "NETCUP",
        "speed": 486,
        "time": "2025-07-27 15:39:49"
    },
    {
        "colo": "Default",
        "ip": "2606:4700:8ca7:7fa3:419:f8f6:22a8:29c2",
        "latency": 4,
        "line": "CM",
        "loss": 0,
        "node": "NETCUP",
        "speed": 396,
        "time": "2025-07-27 15:39:50"
    },
    {
        "colo": "Default",
        "ip": "2606:4700:99eb:dbc0:5bac:207:a2ed:e02f",
        "latency": 3,
        "line": "CM",
        "loss": 0,
        "node": "NETCUP",
        "speed": 382,
        "time": "2025-07-27 15:39:50"
    },
    {
        "colo": "Default",
        "ip": "2606:4700:9ae3:200b:6ae5:e731:51ed:8a43",
        "latency": 4,
        "line": "CT",
        "loss": 0,
        "node": "NETCUP",
        "speed": 518,
        "time": "2025-07-27 15:39:49"
    },
    {
        "colo": "Default",
        "ip": "2606:4700:8ca7:b732:f7ba:4b48:c63b:861a",
        "latency": 4,
        "line": "CT",
        "loss": 0,
        "node": "NETCUP",
        "speed": 492,
        "time": "2025-07-27 15:39:49"
    },
    {
        "colo": "Default",
        "ip": "2606:4700:99eb:f783:fcd5:1bf0:fa5d:e757",
        "latency": 3,
        "line": "CT",
        "loss": 0,
        "node": "NETCUP",
        "speed": 486,
        "time": "2025-07-27 15:39:49"
    },
    {
        "colo": "Default",
        "ip": "2606:4700:8ca7:7fa3:419:f8f6:22a8:29c2",
        "latency": 4,
        "line": "CT",
        "loss": 0,
        "node": "NETCUP",
        "speed": 396,
        "time": "2025-07-27 15:39:50"
    },
    {
        "colo": "Default",
        "ip": "2606:4700:99eb:dbc0:5bac:207:a2ed:e02f",
        "latency": 3,
        "line": "CT",
        "loss": 0,
        "node": "NETCUP",
        "speed": 382,
        "time": "2025-07-27 15:39:50"
    },
    {
        "colo": "Default",
        "ip": "2606:4700:9ae3:200b:6ae5:e731:51ed:8a43",
        "latency": 4,
        "line": "CU",
        "loss": 0,
        "node": "NETCUP",
        "speed": 518,
        "time": "2025-07-27 15:39:49"
    },
    {
        "colo": "Default",
        "ip": "2606:4700:8ca7:b732:f7ba:4b48:c63b:861a",
        "latency": 4,
        "line": "CU",
        "loss": 0,
        "node": "NETCUP",
        "speed": 492,
        "time": "2025-07-27 15:39:49"
    },
    {
        "colo": "Default",
        "ip": "2606:4700:99eb:f783:fcd5:1bf0:fa5d:e757",
        "latency": 3,
        "line": "CU",
        "loss": 0,
        "node": "NETCUP",
        "speed": 486,
        "time": "2025-07-27 15:39:49"
    },
    {
        "colo": "Default",
        "ip": "2606:4700:8ca7:7fa3:419:f8f6:22a8:29c2",
        "latency": 4,
        "line": "CU",
        "loss": 0,
        "node": "NETCUP",
        "speed": 396,
        "time": "2025-07-27 15:39:50"
    },
    {
        "colo": "Default",
        "ip": "2606:4700:99eb:dbc0:5bac:207:a2ed:e02f",
        "latency": 3,
        "line": "CU",
        "loss": 0,
        "node": "NETCUP",
        "speed": 382,
        "time": "2025-07-27 15:39:50"
    }
]