[
    {
        "colo": "Default",
        "ip": "2606:4700:135:f5c4:32f0:2f99:34bc:bd21",
        "latency": 11,
        "line": "CM",
        "loss": 0,
        "node": "CBUS",
        "speed": 562,
        "time": "2024-10-11 07:21:30"
    },
    {
        "colo": "Default",
        "ip": "2606:4700:7000:2b09:bb40:ab34:a616:e10d",
        "latency": 11,
        "line": "CM",
        "loss": 0,
        "node": "CBUS",
        "speed": 553,
        "time": "2024-10-11 07:21:30"
    },
    {
        "colo": "Default",
        "ip": "2606:4700:135:d164:323:7b01:316c:86bc",
        "latency": 11,
        "line": "CM",
        "loss": 0,
        "node": "CBUS",
        "speed": 517,
        "time": "2024-10-11 07:21:30"
    },
    {
        "colo": "Default",
        "ip": "2606:4700:7000:496f:fb62:ebbd:322:7234",
        "latency": 11,
        "line": "CM",
        "loss": 0,
        "node": "CBUS",
        "speed": 373,
        "time": "2024-10-11 07:21:30"
    },
    {
        "colo": "Default",
        "ip": "2606:4700:7000:6102:2e69:2912:470c:dfe7",
        "latency": 11,
        "line": "CM",
        "loss": 0,
        "node": "CBUS",
        "speed": 370,
        "time": "2024-10-11 07:21:30"
    },
    {
        "colo": "Default",
        "ip": "2606:4700:85d6:4ddf:3c5c:882f:7e15:16a2",
        "latency": 26,
        "line": "CT",
        "loss": 0,
        "node": "WEBH",
        "speed": 309,
        "time": "2024-10-11 07:15:39"
    },
    {
        "colo": "Default",
        "ip": "2606:4700:85d6:6d1c:68aa:9496:bca9:df61",
        "latency": 24,
        "line": "CT",
        "loss": 0,
        "node": "WEBH",
        "speed": 308,
        "time": "2024-10-11 07:15:39"
    },
    {
        "colo": "Default",
        "ip": "2606:4700:85d6:a5d8:52f0:824:3598:4bd5",
        "latency": 25,
        "line": "CT",
        "loss": 0,
        "node": "WEBH",
        "speed": 308,
        "time": "2024-10-11 07:15:39"
    },
    {
        "colo": "Default",
        "ip": "2606:4700:85d6:e620:a483:62e:71f9:3379",
        "latency": 24,
        "line": "CT",
        "loss": 0,
        "node": "WEBH",
        "speed": 308,
        "time": "2024-10-11 07:15:39"
    },
    {
        "colo": "Default",
        "ip": "2606:4700:85d6:1dde:1fce:9853:ecb2:3e",
        "latency": 25,
        "line": "CT",
        "loss": 0,
        "node": "WEBH",
        "speed": 308,
        "time": "2024-10-11 07:15:39"
    },
    {
        "colo": "Default",
        "ip": "2606:4700:135:f5c4:32f0:2f99:34bc:bd21",
        "latency": 11,
        "line": "CU",
        "loss": 0,
        "node": "CBUS",
        "speed": 562,
        "time": "2024-10-11 07:21:30"
    },
    {
        "colo": "Default",
        "ip": "2606:4700:7000:2b09:bb40:ab34:a616:e10d",
        "latency": 11,
        "line": "CU",
        "loss": 0,
        "node": "CBUS",
        "speed": 553,
        "time": "2024-10-11 07:21:30"
    },
    {
        "colo": "Default",
        "ip": "2606:4700:135:d164:323:7b01:316c:86bc",
        "latency": 11,
        "line": "CU",
        "loss": 0,
        "node": "CBUS",
        "speed": 517,
        "time": "2024-10-11 07:21:30"
    },
    {
        "colo": "Default",
        "ip": "2606:4700:7000:496f:fb62:ebbd:322:7234",
        "latency": 11,
        "line": "CU",
        "loss": 0,
        "node": "CBUS",
        "speed": 373,
        "time": "2024-10-11 07:21:30"
    },
    {
        "colo": "Default",
        "ip": "2606:4700:7000:6102:2e69:2912:470c:dfe7",
        "latency": 11,
        "line": "CU",
        "loss": 0,
        "node": "CBUS",
        "speed": 370,
        "time": "2024-10-11 07:21:30"
    }
]