[
    {
        "colo": "Default",
        "ip": "2606:4700:99ea:10ad:24c1:e76f:f67d:c166",
        "latency": 21,
        "line": "CM",
        "loss": 0,
        "node": "WEBH",
        "speed": 310,
        "time": "2024-12-17 17:04:55"
    },
    {
        "colo": "Default",
        "ip": "2606:4700:99ea:297e:93:1634:26f6:5dc5",
        "latency": 20,
        "line": "CM",
        "loss": 0,
        "node": "WEBH",
        "speed": 309,
        "time": "2024-12-17 17:04:57"
    },
    {
        "colo": "Default",
        "ip": "2606:4700:99ea:a96:ccfc:b7fd:94d8:7bc0",
        "latency": 21,
        "line": "CM",
        "loss": 0,
        "node": "WEBH",
        "speed": 307,
        "time": "2024-12-17 17:04:58"
    },
    {
        "colo": "Default",
        "ip": "2606:4700:8de9:fb17:f6a3:b51c:7d3e:ee9b",
        "latency": 21,
        "line": "CM",
        "loss": 0,
        "node": "WEBH",
        "speed": 307,
        "time": "2024-12-17 17:04:58"
    },
    {
        "colo": "Default",
        "ip": "2606:4700:8de9:24d4:35b:cc3b:b34c:91b2",
        "latency": 20,
        "line": "CM",
        "loss": 0,
        "node": "WEBH",
        "speed": 307,
        "time": "2024-12-17 17:04:56"
    },
    {
        "colo": "Default",
        "ip": "2606:4700:99ea:10ad:24c1:e76f:f67d:c166",
        "latency": 21,
        "line": "CT",
        "loss": 0,
        "node": "WEBH",
        "speed": 310,
        "time": "2024-12-17 17:04:55"
    },
    {
        "colo": "Default",
        "ip": "2606:4700:99ea:297e:93:1634:26f6:5dc5",
        "latency": 20,
        "line": "CT",
        "loss": 0,
        "node": "WEBH",
        "speed": 309,
        "time": "2024-12-17 17:04:57"
    },
    {
        "colo": "Default",
        "ip": "2606:4700:99ea:a96:ccfc:b7fd:94d8:7bc0",
        "latency": 21,
        "line": "CT",
        "loss": 0,
        "node": "WEBH",
        "speed": 307,
        "time": "2024-12-17 17:04:58"
    },
    {
        "colo": "Default",
        "ip": "2606:4700:8de9:fb17:f6a3:b51c:7d3e:ee9b",
        "latency": 21,
        "line": "CT",
        "loss": 0,
        "node": "WEBH",
        "speed": 307,
        "time": "2024-12-17 17:04:58"
    },
    {
        "colo": "Default",
        "ip": "2606:4700:8de9:24d4:35b:cc3b:b34c:91b2",
        "latency": 20,
        "line": "CT",
        "loss": 0,
        "node": "WEBH",
        "speed": 307,
        "time": "2024-12-17 17:04:56"
    },
    {
        "colo": "Default",
        "ip": "2606:4700:99ea:10ad:24c1:e76f:f67d:c166",
        "latency": 21,
        "line": "CU",
        "loss": 0,
        "node": "WEBH",
        "speed": 310,
        "time": "2024-12-17 17:04:55"
    },
    {
        "colo": "Default",
        "ip": "2606:4700:99ea:297e:93:1634:26f6:5dc5",
        "latency": 20,
        "line": "CU",
        "loss": 0,
        "node": "WEBH",
        "speed": 309,
        "time": "2024-12-17 17:04:57"
    },
    {
        "colo": "Default",
        "ip": "2606:4700:99ea:a96:ccfc:b7fd:94d8:7bc0",
        "latency": 21,
        "line": "CU",
        "loss": 0,
        "node": "WEBH",
        "speed": 307,
        "time": "2024-12-17 17:04:58"
    },
    {
        "colo": "Default",
        "ip": "2606:4700:8de9:fb17:f6a3:b51c:7d3e:ee9b",
        "latency": 21,
        "line": "CU",
        "loss": 0,
        "node": "WEBH",
        "speed": 307,
        "time": "2024-12-17 17:04:58"
    },
    {
        "colo": "Default",
        "ip": "2606:4700:8de9:24d4:35b:cc3b:b34c:91b2",
        "latency": 20,
        "line": "CU",
        "loss": 0,
        "node": "WEBH",
        "speed": 307,
        "time": "2024-12-17 17:04:56"
    }
]