[
    {
        "colo": "Default",
        "ip": "2606:4700:8d9b:bfe4:528b:407e:8f01:7d07",
        "latency": 160,
        "line": "CM",
        "loss": 0,
        "node": "CBUS",
        "speed": 578,
        "time": "2024-11-18 13:47:20"
    },
    {
        "colo": "Default",
        "ip": "2606:4700:8d9b:9352:c486:991f:f547:f18f",
        "latency": 153,
        "line": "CM",
        "loss": 0,
        "node": "CBUS",
        "speed": 488,
        "time": "2024-11-18 13:47:20"
    },
    {
        "colo": "Default",
        "ip": "2606:4700:4407:ed20:b097:78b8:bbd4:bfff",
        "latency": 16,
        "line": "CM",
        "loss": 0,
        "node": "CBUS",
        "speed": 366,
        "time": "2024-11-18 13:47:20"
    },
    {
        "colo": "Default",
        "ip": "2606:4700:4407:c332:3244:6fd7:c264:8884",
        "latency": 17,
        "line": "CM",
        "loss": 0,
        "node": "CBUS",
        "speed": 364,
        "time": "2024-11-18 13:47:20"
    },
    {
        "colo": "Default",
        "ip": "2606:4700:4407:908f:d5c0:c897:17f0:c96e",
        "latency": 13,
        "line": "CM",
        "loss": 0,
        "node": "CBUS",
        "speed": 362,
        "time": "2024-11-18 13:47:20"
    },
    {
        "colo": "Default",
        "ip": "2606:4700:9ad2:370f:7f7b:f632:326:6eef",
        "latency": 25,
        "line": "CT",
        "loss": 0,
        "node": "WEBH",
        "speed": 310,
        "time": "2024-11-18 13:55:14"
    },
    {
        "colo": "Default",
        "ip": "2606:4700:9ad2:5cc3:f02c:d0f2:cfa0:739a",
        "latency": 20,
        "line": "CT",
        "loss": 0,
        "node": "WEBH",
        "speed": 308,
        "time": "2024-11-18 13:55:14"
    },
    {
        "colo": "Default",
        "ip": "2606:4700:9ad2:8e10:783f:e0cf:ca4b:3e14",
        "latency": 25,
        "line": "CT",
        "loss": 0,
        "node": "WEBH",
        "speed": 308,
        "time": "2024-11-18 13:55:14"
    },
    {
        "colo": "Default",
        "ip": "2606:4700:9ad2:d959:fe82:8a33:a96e:3123",
        "latency": 25,
        "line": "CT",
        "loss": 0,
        "node": "WEBH",
        "speed": 308,
        "time": "2024-11-18 13:55:14"
    },
    {
        "colo": "Default",
        "ip": "2606:4700:9ad2:ae36:1c8d:f220:4e9d:d756",
        "latency": 24,
        "line": "CT",
        "loss": 0,
        "node": "WEBH",
        "speed": 307,
        "time": "2024-11-18 13:55:14"
    },
    {
        "colo": "Default",
        "ip": "2606:4700:8d9b:bfe4:528b:407e:8f01:7d07",
        "latency": 160,
        "line": "CU",
        "loss": 0,
        "node": "CBUS",
        "speed": 578,
        "time": "2024-11-18 13:47:20"
    },
    {
        "colo": "Default",
        "ip": "2606:4700:8d9b:9352:c486:991f:f547:f18f",
        "latency": 153,
        "line": "CU",
        "loss": 0,
        "node": "CBUS",
        "speed": 488,
        "time": "2024-11-18 13:47:20"
    },
    {
        "colo": "Default",
        "ip": "2606:4700:4407:ed20:b097:78b8:bbd4:bfff",
        "latency": 16,
        "line": "CU",
        "loss": 0,
        "node": "CBUS",
        "speed": 366,
        "time": "2024-11-18 13:47:20"
    },
    {
        "colo": "Default",
        "ip": "2606:4700:4407:c332:3244:6fd7:c264:8884",
        "latency": 17,
        "line": "CU",
        "loss": 0,
        "node": "CBUS",
        "speed": 364,
        "time": "2024-11-18 13:47:20"
    },
    {
        "colo": "Default",
        "ip": "2606:4700:4407:908f:d5c0:c897:17f0:c96e",
        "latency": 13,
        "line": "CU",
        "loss": 0,
        "node": "CBUS",
        "speed": 362,
        "time": "2024-11-18 13:47:20"
    }
]