[
    {
        "colo": "Default",
        "ip": "2606:4700:90cb:f4af:6e9b:2e96:ae35:4f21",
        "latency": 4,
        "line": "CM",
        "loss": 0,
        "node": "NETCUP",
        "speed": 576,
        "time": "2025-07-16 06:50:18"
    },
    {
        "colo": "Default",
        "ip": "2606:4700:8392:ebd7:a151:49d4:8757:ecca",
        "latency": 3,
        "line": "CM",
        "loss": 0,
        "node": "NETCUP",
        "speed": 542,
        "time": "2025-07-16 06:50:18"
    },
    {
        "colo": "Default",
        "ip": "2606:4700:9647:36f8:2f23:5252:5812:c1e4",
        "latency": 3,
        "line": "CM",
        "loss": 0,
        "node": "NETCUP",
        "speed": 479,
        "time": "2025-07-16 06:50:18"
    },
    {
        "colo": "Default",
        "ip": "2606:4700:9647:a25d:312d:8acf:f695:4fe0",
        "latency": 4,
        "line": "CM",
        "loss": 0,
        "node": "NETCUP",
        "speed": 426,
        "time": "2025-07-16 06:50:18"
    },
    {
        "colo": "Default",
        "ip": "2606:4700:8392:1d5:45f2:30ce:4deb:4df0",
        "latency": 3,
        "line": "CM",
        "loss": 0,
        "node": "NETCUP",
        "speed": 425,
        "time": "2025-07-16 06:50:18"
    },
    {
        "colo": "Default",
        "ip": "2606:4700:90cb:f4af:6e9b:2e96:ae35:4f21",
        "latency": 4,
        "line": "CT",
        "loss": 0,
        "node": "NETCUP",
        "speed": 576,
        "time": "2025-07-16 06:50:18"
    },
    {
        "colo": "Default",
        "ip": "2606:4700:8392:ebd7:a151:49d4:8757:ecca",
        "latency": 3,
        "line": "CT",
        "loss": 0,
        "node": "NETCUP",
        "speed": 542,
        "time": "2025-07-16 06:50:18"
    },
    {
        "colo": "Default",
        "ip": "2606:4700:9647:36f8:2f23:5252:5812:c1e4",
        "latency": 3,
        "line": "CT",
        "loss": 0,
        "node": "NETCUP",
        "speed": 479,
        "time": "2025-07-16 06:50:18"
    },
    {
        "colo": "Default",
        "ip": "2606:4700:9647:a25d:312d:8acf:f695:4fe0",
        "latency": 4,
        "line": "CT",
        "loss": 0,
        "node": "NETCUP",
        "speed": 426,
        "time": "2025-07-16 06:50:18"
    },
    {
        "colo": "Default",
        "ip": "2606:4700:8392:1d5:45f2:30ce:4deb:4df0",
        "latency": 3,
        "line": "CT",
        "loss": 0,
        "node": "NETCUP",
        "speed": 425,
        "time": "2025-07-16 06:50:18"
    },
    {
        "colo": "Default",
        "ip": "2606:4700:90cb:f4af:6e9b:2e96:ae35:4f21",
        "latency": 4,
        "line": "CU",
        "loss": 0,
        "node": "NETCUP",
        "speed": 576,
        "time": "2025-07-16 06:50:18"
    },
    {
        "colo": "Default",
        "ip": "2606:4700:8392:ebd7:a151:49d4:8757:ecca",
        "latency": 3,
        "line": "CU",
        "loss": 0,
        "node": "NETCUP",
        "speed": 542,
        "time": "2025-07-16 06:50:18"
    },
    {
        "colo": "Default",
        "ip": "2606:4700:9647:36f8:2f23:5252:5812:c1e4",
        "latency": 3,
        "line": "CU",
        "loss": 0,
        "node": "NETCUP",
        "speed": 479,
        "time": "2025-07-16 06:50:18"
    },
    {
        "colo": "Default",
        "ip": "2606:4700:9647:a25d:312d:8acf:f695:4fe0",
        "latency": 4,
        "line": "CU",
        "loss": 0,
        "node": "NETCUP",
        "speed": 426,
        "time": "2025-07-16 06:50:18"
    },
    {
        "colo": "Default",
        "ip": "2606:4700:8392:1d5:45f2:30ce:4deb:4df0",
        "latency": 3,
        "line": "CU",
        "loss": 0,
        "node": "NETCUP",
        "speed": 425,
        "time": "2025-07-16 06:50:18"
    }
]