[
    {
        "colo": "Default",
        "ip": "2606:4700:964e:b9ff:1d26:dfc3:3c62:fd1c",
        "latency": 4,
        "line": "CM",
        "loss": 0,
        "node": "NETCUP",
        "speed": 602,
        "time": "2025-06-13 17:26:11"
    },
    {
        "colo": "Default",
        "ip": "2606:4700:3006:54d9:86c4:35f1:57ac:a3ac",
        "latency": 3,
        "line": "CM",
        "loss": 0,
        "node": "NETCUP",
        "speed": 436,
        "time": "2025-06-13 17:26:11"
    },
    {
        "colo": "Default",
        "ip": "2606:4700:24:a4a:4e53:b833:f11c:255e",
        "latency": 4,
        "line": "CM",
        "loss": 0,
        "node": "NETCUP",
        "speed": 436,
        "time": "2025-06-13 17:26:11"
    },
    {
        "colo": "Default",
        "ip": "2606:4700:24:2483:dfa2:4d6b:72b0:5d1d",
        "latency": 4,
        "line": "CM",
        "loss": 0,
        "node": "NETCUP",
        "speed": 435,
        "time": "2025-06-13 17:26:11"
    },
    {
        "colo": "Default",
        "ip": "2606:4700:90db:af1c:a25b:c416:2db9:9660",
        "latency": 3,
        "line": "CM",
        "loss": 0,
        "node": "NETCUP",
        "speed": 335,
        "time": "2025-06-13 17:26:11"
    },
    {
        "colo": "Default",
        "ip": "2606:4700:964e:b9ff:1d26:dfc3:3c62:fd1c",
        "latency": 4,
        "line": "CT",
        "loss": 0,
        "node": "NETCUP",
        "speed": 602,
        "time": "2025-06-13 17:26:11"
    },
    {
        "colo": "Default",
        "ip": "2606:4700:3006:54d9:86c4:35f1:57ac:a3ac",
        "latency": 3,
        "line": "CT",
        "loss": 0,
        "node": "NETCUP",
        "speed": 436,
        "time": "2025-06-13 17:26:11"
    },
    {
        "colo": "Default",
        "ip": "2606:4700:24:a4a:4e53:b833:f11c:255e",
        "latency": 4,
        "line": "CT",
        "loss": 0,
        "node": "NETCUP",
        "speed": 436,
        "time": "2025-06-13 17:26:11"
    },
    {
        "colo": "Default",
        "ip": "2606:4700:24:2483:dfa2:4d6b:72b0:5d1d",
        "latency": 4,
        "line": "CT",
        "loss": 0,
        "node": "NETCUP",
        "speed": 435,
        "time": "2025-06-13 17:26:11"
    },
    {
        "colo": "Default",
        "ip": "2606:4700:90db:af1c:a25b:c416:2db9:9660",
        "latency": 3,
        "line": "CT",
        "loss": 0,
        "node": "NETCUP",
        "speed": 335,
        "time": "2025-06-13 17:26:11"
    },
    {
        "colo": "Default",
        "ip": "2606:4700:964e:b9ff:1d26:dfc3:3c62:fd1c",
        "latency": 4,
        "line": "CU",
        "loss": 0,
        "node": "NETCUP",
        "speed": 602,
        "time": "2025-06-13 17:26:11"
    },
    {
        "colo": "Default",
        "ip": "2606:4700:3006:54d9:86c4:35f1:57ac:a3ac",
        "latency": 3,
        "line": "CU",
        "loss": 0,
        "node": "NETCUP",
        "speed": 436,
        "time": "2025-06-13 17:26:11"
    },
    {
        "colo": "Default",
        "ip": "2606:4700:24:a4a:4e53:b833:f11c:255e",
        "latency": 4,
        "line": "CU",
        "loss": 0,
        "node": "NETCUP",
        "speed": 436,
        "time": "2025-06-13 17:26:11"
    },
    {
        "colo": "Default",
        "ip": "2606:4700:24:2483:dfa2:4d6b:72b0:5d1d",
        "latency": 4,
        "line": "CU",
        "loss": 0,
        "node": "NETCUP",
        "speed": 435,
        "time": "2025-06-13 17:26:11"
    },
    {
        "colo": "Default",
        "ip": "2606:4700:90db:af1c:a25b:c416:2db9:9660",
        "latency": 3,
        "line": "CU",
        "loss": 0,
        "node": "NETCUP",
        "speed": 335,
        "time": "2025-06-13 17:26:11"
    }
]