[
    {
        "colo": "Default",
        "ip": "2606:4700:9645:7fc4:787b:531a:43cf:c72",
        "latency": 20,
        "line": "CM",
        "loss": 0,
        "node": "WEBH",
        "speed": 308,
        "time": "2025-02-05 03:24:25"
    },
    {
        "colo": "Default",
        "ip": "2606:4700:8d7a:1d9c:92e1:32a1:b4a5:c238",
        "latency": 20,
        "line": "CM",
        "loss": 0,
        "node": "WEBH",
        "speed": 308,
        "time": "2025-02-05 03:24:24"
    },
    {
        "colo": "Default",
        "ip": "2606:4700:8d7a:b5b1:6f9e:671a:26ea:3620",
        "latency": 20,
        "line": "CM",
        "loss": 0,
        "node": "WEBH",
        "speed": 308,
        "time": "2025-02-05 03:24:24"
    },
    {
        "colo": "Default",
        "ip": "2606:4700:8d7a:c145:5ec5:a36:3192:6f62",
        "latency": 24,
        "line": "CM",
        "loss": 0,
        "node": "WEBH",
        "speed": 307,
        "time": "2025-02-05 03:24:23"
    },
    {
        "colo": "Default",
        "ip": "2606:4700:8d7a:f619:314d:214d:3579:df3c",
        "latency": 22,
        "line": "CM",
        "loss": 0,
        "node": "WEBH",
        "speed": 307,
        "time": "2025-02-05 03:24:22"
    },
    {
        "colo": "Default",
        "ip": "2606:4700:9645:7fc4:787b:531a:43cf:c72",
        "latency": 20,
        "line": "CT",
        "loss": 0,
        "node": "WEBH",
        "speed": 308,
        "time": "2025-02-05 03:24:25"
    },
    {
        "colo": "Default",
        "ip": "2606:4700:8d7a:1d9c:92e1:32a1:b4a5:c238",
        "latency": 20,
        "line": "CT",
        "loss": 0,
        "node": "WEBH",
        "speed": 308,
        "time": "2025-02-05 03:24:24"
    },
    {
        "colo": "Default",
        "ip": "2606:4700:8d7a:b5b1:6f9e:671a:26ea:3620",
        "latency": 20,
        "line": "CT",
        "loss": 0,
        "node": "WEBH",
        "speed": 308,
        "time": "2025-02-05 03:24:24"
    },
    {
        "colo": "Default",
        "ip": "2606:4700:8d7a:c145:5ec5:a36:3192:6f62",
        "latency": 24,
        "line": "CT",
        "loss": 0,
        "node": "WEBH",
        "speed": 307,
        "time": "2025-02-05 03:24:23"
    },
    {
        "colo": "Default",
        "ip": "2606:4700:8d7a:f619:314d:214d:3579:df3c",
        "latency": 22,
        "line": "CT",
        "loss": 0,
        "node": "WEBH",
        "speed": 307,
        "time": "2025-02-05 03:24:22"
    },
    {
        "colo": "Default",
        "ip": "2606:4700:9645:7fc4:787b:531a:43cf:c72",
        "latency": 20,
        "line": "CU",
        "loss": 0,
        "node": "WEBH",
        "speed": 308,
        "time": "2025-02-05 03:24:25"
    },
    {
        "colo": "Default",
        "ip": "2606:4700:8d7a:1d9c:92e1:32a1:b4a5:c238",
        "latency": 20,
        "line": "CU",
        "loss": 0,
        "node": "WEBH",
        "speed": 308,
        "time": "2025-02-05 03:24:24"
    },
    {
        "colo": "Default",
        "ip": "2606:4700:8d7a:b5b1:6f9e:671a:26ea:3620",
        "latency": 20,
        "line": "CU",
        "loss": 0,
        "node": "WEBH",
        "speed": 308,
        "time": "2025-02-05 03:24:24"
    },
    {
        "colo": "Default",
        "ip": "2606:4700:8d7a:c145:5ec5:a36:3192:6f62",
        "latency": 24,
        "line": "CU",
        "loss": 0,
        "node": "WEBH",
        "speed": 307,
        "time": "2025-02-05 03:24:23"
    },
    {
        "colo": "Default",
        "ip": "2606:4700:8d7a:f619:314d:214d:3579:df3c",
        "latency": 22,
        "line": "CU",
        "loss": 0,
        "node": "WEBH",
        "speed": 307,
        "time": "2025-02-05 03:24:22"
    }
]