[
    {
        "colo": "Default",
        "ip": "2606:4700:91ba:89f3:f31:988c:36a5:24cc",
        "latency": 3,
        "line": "CM",
        "loss": 0,
        "node": "NETCUP",
        "speed": 610,
        "time": "2025-05-19 12:34:46"
    },
    {
        "colo": "Default",
        "ip": "2606:4700:3006:8ff9:ee6a:3c9:ef8c:d7d7",
        "latency": 14,
        "line": "CM",
        "loss": 0,
        "node": "NETCUP",
        "speed": 608,
        "time": "2025-05-19 12:34:46"
    },
    {
        "colo": "Default",
        "ip": "2606:4700:9644:145e:c515:42bc:506f:da95",
        "latency": 4,
        "line": "CM",
        "loss": 0,
        "node": "NETCUP",
        "speed": 464,
        "time": "2025-05-19 12:34:46"
    },
    {
        "colo": "Default",
        "ip": "2606:4700:9644:3eb0:29e2:4b93:1c76:ff7",
        "latency": 3,
        "line": "CM",
        "loss": 0,
        "node": "NETCUP",
        "speed": 424,
        "time": "2025-05-19 12:34:46"
    },
    {
        "colo": "Default",
        "ip": "2606:4700:91ba:5590:9322:7d75:884a:6951",
        "latency": 3,
        "line": "CM",
        "loss": 0,
        "node": "NETCUP",
        "speed": 388,
        "time": "2025-05-19 12:34:45"
    },
    {
        "colo": "Default",
        "ip": "2606:4700:91ba:89f3:f31:988c:36a5:24cc",
        "latency": 3,
        "line": "CT",
        "loss": 0,
        "node": "NETCUP",
        "speed": 610,
        "time": "2025-05-19 12:34:46"
    },
    {
        "colo": "Default",
        "ip": "2606:4700:3006:8ff9:ee6a:3c9:ef8c:d7d7",
        "latency": 14,
        "line": "CT",
        "loss": 0,
        "node": "NETCUP",
        "speed": 608,
        "time": "2025-05-19 12:34:46"
    },
    {
        "colo": "Default",
        "ip": "2606:4700:9644:145e:c515:42bc:506f:da95",
        "latency": 4,
        "line": "CT",
        "loss": 0,
        "node": "NETCUP",
        "speed": 464,
        "time": "2025-05-19 12:34:46"
    },
    {
        "colo": "Default",
        "ip": "2606:4700:9644:3eb0:29e2:4b93:1c76:ff7",
        "latency": 3,
        "line": "CT",
        "loss": 0,
        "node": "NETCUP",
        "speed": 424,
        "time": "2025-05-19 12:34:46"
    },
    {
        "colo": "Default",
        "ip": "2606:4700:91ba:5590:9322:7d75:884a:6951",
        "latency": 3,
        "line": "CT",
        "loss": 0,
        "node": "NETCUP",
        "speed": 388,
        "time": "2025-05-19 12:34:45"
    },
    {
        "colo": "Default",
        "ip": "2606:4700:91ba:89f3:f31:988c:36a5:24cc",
        "latency": 3,
        "line": "CU",
        "loss": 0,
        "node": "NETCUP",
        "speed": 610,
        "time": "2025-05-19 12:34:46"
    },
    {
        "colo": "Default",
        "ip": "2606:4700:3006:8ff9:ee6a:3c9:ef8c:d7d7",
        "latency": 14,
        "line": "CU",
        "loss": 0,
        "node": "NETCUP",
        "speed": 608,
        "time": "2025-05-19 12:34:46"
    },
    {
        "colo": "Default",
        "ip": "2606:4700:9644:145e:c515:42bc:506f:da95",
        "latency": 4,
        "line": "CU",
        "loss": 0,
        "node": "NETCUP",
        "speed": 464,
        "time": "2025-05-19 12:34:46"
    },
    {
        "colo": "Default",
        "ip": "2606:4700:9644:3eb0:29e2:4b93:1c76:ff7",
        "latency": 3,
        "line": "CU",
        "loss": 0,
        "node": "NETCUP",
        "speed": 424,
        "time": "2025-05-19 12:34:46"
    },
    {
        "colo": "Default",
        "ip": "2606:4700:91ba:5590:9322:7d75:884a:6951",
        "latency": 3,
        "line": "CU",
        "loss": 0,
        "node": "NETCUP",
        "speed": 388,
        "time": "2025-05-19 12:34:45"
    }
]