[
    {
        "colo": "Default",
        "ip": "2606:4700:90c2:df06:9024:295c:7900:97da",
        "latency": 159,
        "line": "CM",
        "loss": 0,
        "node": "CBUS",
        "speed": 507,
        "time": "2024-12-02 07:29:27"
    },
    {
        "colo": "Default",
        "ip": "2606:4700:9a99:cfb4:4aee:f15f:d709:3fe3",
        "latency": 156,
        "line": "CM",
        "loss": 0,
        "node": "CBUS",
        "speed": 507,
        "time": "2024-12-02 07:29:27"
    },
    {
        "colo": "Default",
        "ip": "2606:4700:90c2:43a4:9fff:a89a:a30e:8748",
        "latency": 151,
        "line": "CM",
        "loss": 0,
        "node": "CBUS",
        "speed": 504,
        "time": "2024-12-02 07:29:26"
    },
    {
        "colo": "Default",
        "ip": "2606:4700:9a99:e799:5e64:d40d:66d8:ca15",
        "latency": 159,
        "line": "CM",
        "loss": 0,
        "node": "CBUS",
        "speed": 419,
        "time": "2024-12-02 07:29:27"
    },
    {
        "colo": "Default",
        "ip": "2606:4700:90c2:49dd:756d:c85e:42aa:fefe",
        "latency": 148,
        "line": "CM",
        "loss": 0,
        "node": "CBUS",
        "speed": 418,
        "time": "2024-12-02 07:29:26"
    },
    {
        "colo": "Default",
        "ip": "2606:4700:3024:5b0f:5388:190d:d711:c66d",
        "latency": 1,
        "line": "CT",
        "loss": 0,
        "node": "WEBH",
        "speed": 309,
        "time": "2024-12-02 07:25:07"
    },
    {
        "colo": "Default",
        "ip": "2606:4700:8d71:64ec:9a1c:3d65:ba8c:a31f",
        "latency": 20,
        "line": "CT",
        "loss": 0,
        "node": "WEBH",
        "speed": 309,
        "time": "2024-12-02 07:25:06"
    },
    {
        "colo": "Default",
        "ip": "2606:4700:8d71:61f0:eb16:8ac6:c676:ad7d",
        "latency": 20,
        "line": "CT",
        "loss": 0,
        "node": "WEBH",
        "speed": 307,
        "time": "2024-12-02 07:25:08"
    },
    {
        "colo": "Default",
        "ip": "2606:4700:8d71:a155:9979:72bc:b902:6c5d",
        "latency": 25,
        "line": "CT",
        "loss": 0,
        "node": "WEBH",
        "speed": 307,
        "time": "2024-12-02 07:25:08"
    },
    {
        "colo": "Default",
        "ip": "2606:4700:8d71:5eab:5c3a:81c5:a1ca:a31b",
        "latency": 20,
        "line": "CT",
        "loss": 0,
        "node": "WEBH",
        "speed": 307,
        "time": "2024-12-02 07:25:05"
    },
    {
        "colo": "Default",
        "ip": "2606:4700:90c2:df06:9024:295c:7900:97da",
        "latency": 159,
        "line": "CU",
        "loss": 0,
        "node": "CBUS",
        "speed": 507,
        "time": "2024-12-02 07:29:27"
    },
    {
        "colo": "Default",
        "ip": "2606:4700:9a99:cfb4:4aee:f15f:d709:3fe3",
        "latency": 156,
        "line": "CU",
        "loss": 0,
        "node": "CBUS",
        "speed": 507,
        "time": "2024-12-02 07:29:27"
    },
    {
        "colo": "Default",
        "ip": "2606:4700:90c2:43a4:9fff:a89a:a30e:8748",
        "latency": 151,
        "line": "CU",
        "loss": 0,
        "node": "CBUS",
        "speed": 504,
        "time": "2024-12-02 07:29:26"
    },
    {
        "colo": "Default",
        "ip": "2606:4700:9a99:e799:5e64:d40d:66d8:ca15",
        "latency": 159,
        "line": "CU",
        "loss": 0,
        "node": "CBUS",
        "speed": 419,
        "time": "2024-12-02 07:29:27"
    },
    {
        "colo": "Default",
        "ip": "2606:4700:90c2:49dd:756d:c85e:42aa:fefe",
        "latency": 148,
        "line": "CU",
        "loss": 0,
        "node": "CBUS",
        "speed": 418,
        "time": "2024-12-02 07:29:26"
    }
]