[
    {
        "colo": "Default",
        "ip": "2606:4700:90cb:b47a:c16:f894:4fb0:fa5d",
        "latency": 149,
        "line": "CM",
        "loss": 0,
        "node": "CBUS",
        "speed": 551,
        "time": "2024-11-09 16:45:58"
    },
    {
        "colo": "Default",
        "ip": "2606:4700:90cb:15e3:8272:6a86:212a:8ebd",
        "latency": 160,
        "line": "CM",
        "loss": 0,
        "node": "CBUS",
        "speed": 508,
        "time": "2024-11-09 16:45:58"
    },
    {
        "colo": "Default",
        "ip": "2606:4700:90cb:3a4a:1bb8:9a88:1830:5791",
        "latency": 160,
        "line": "CM",
        "loss": 0,
        "node": "CBUS",
        "speed": 490,
        "time": "2024-11-09 16:45:58"
    },
    {
        "colo": "Default",
        "ip": "2606:4700:90cb:4eb4:ed:c233:3183:b3d4",
        "latency": 146,
        "line": "CM",
        "loss": 0,
        "node": "CBUS",
        "speed": 473,
        "time": "2024-11-09 16:45:58"
    },
    {
        "colo": "Default",
        "ip": "2606:4700:90cb:e8d3:c563:92ed:2a32:597f",
        "latency": 159,
        "line": "CM",
        "loss": 0,
        "node": "CBUS",
        "speed": 444,
        "time": "2024-11-09 16:45:58"
    },
    {
        "colo": "Default",
        "ip": "2606:4700:3005:27dd:1610:89aa:be55:475c",
        "latency": 1,
        "line": "CT",
        "loss": 0,
        "node": "WEBH",
        "speed": 310,
        "time": "2024-11-09 16:55:20"
    },
    {
        "colo": "Default",
        "ip": "2606:4700:3005:155a:165b:716:bcbb:729c",
        "latency": 1,
        "line": "CT",
        "loss": 0,
        "node": "WEBH",
        "speed": 309,
        "time": "2024-11-09 16:55:20"
    },
    {
        "colo": "Default",
        "ip": "2606:4700:3005:6388:ed7a:dceb:7fa8:8aea",
        "latency": 1,
        "line": "CT",
        "loss": 0,
        "node": "WEBH",
        "speed": 308,
        "time": "2024-11-09 16:55:20"
    },
    {
        "colo": "Default",
        "ip": "2606:4700:3005:1e01:6da9:115b:4910:73a6",
        "latency": 1,
        "line": "CT",
        "loss": 0,
        "node": "WEBH",
        "speed": 308,
        "time": "2024-11-09 16:55:20"
    },
    {
        "colo": "Default",
        "ip": "2606:4700:3005:24d2:3ec:2f1:1cbf:512a",
        "latency": 1,
        "line": "CT",
        "loss": 0,
        "node": "WEBH",
        "speed": 307,
        "time": "2024-11-09 16:55:19"
    },
    {
        "colo": "Default",
        "ip": "2606:4700:90cb:b47a:c16:f894:4fb0:fa5d",
        "latency": 149,
        "line": "CU",
        "loss": 0,
        "node": "CBUS",
        "speed": 551,
        "time": "2024-11-09 16:45:58"
    },
    {
        "colo": "Default",
        "ip": "2606:4700:90cb:15e3:8272:6a86:212a:8ebd",
        "latency": 160,
        "line": "CU",
        "loss": 0,
        "node": "CBUS",
        "speed": 508,
        "time": "2024-11-09 16:45:58"
    },
    {
        "colo": "Default",
        "ip": "2606:4700:90cb:3a4a:1bb8:9a88:1830:5791",
        "latency": 160,
        "line": "CU",
        "loss": 0,
        "node": "CBUS",
        "speed": 490,
        "time": "2024-11-09 16:45:58"
    },
    {
        "colo": "Default",
        "ip": "2606:4700:90cb:4eb4:ed:c233:3183:b3d4",
        "latency": 146,
        "line": "CU",
        "loss": 0,
        "node": "CBUS",
        "speed": 473,
        "time": "2024-11-09 16:45:58"
    },
    {
        "colo": "Default",
        "ip": "2606:4700:90cb:e8d3:c563:92ed:2a32:597f",
        "latency": 159,
        "line": "CU",
        "loss": 0,
        "node": "CBUS",
        "speed": 444,
        "time": "2024-11-09 16:45:58"
    }
]