[
    {
        "colo": "Default",
        "ip": "2606:4700:3:31bf:6960:5e73:eb73:5d53",
        "latency": 11,
        "line": "CM",
        "loss": 0,
        "node": "CBUS",
        "speed": 625,
        "time": "2024-12-04 04:29:44"
    },
    {
        "colo": "Default",
        "ip": "2606:4700:3:6a69:36ae:11ca:6fd9:c9e0",
        "latency": 11,
        "line": "CM",
        "loss": 0,
        "node": "CBUS",
        "speed": 537,
        "time": "2024-12-04 04:29:44"
    },
    {
        "colo": "Default",
        "ip": "2606:4700:4403:fe6e:37bc:d441:1afc:b63c",
        "latency": 11,
        "line": "CM",
        "loss": 0,
        "node": "CBUS",
        "speed": 531,
        "time": "2024-12-04 04:29:43"
    },
    {
        "colo": "Default",
        "ip": "2606:4700:3:7af9:42c3:c98b:9753:5ccc",
        "latency": 11,
        "line": "CM",
        "loss": 0,
        "node": "CBUS",
        "speed": 502,
        "time": "2024-12-04 04:29:43"
    },
    {
        "colo": "Default",
        "ip": "2606:4700:4403:6e6d:8711:de0:6e0c:b046",
        "latency": 11,
        "line": "CM",
        "loss": 0,
        "node": "CBUS",
        "speed": 386,
        "time": "2024-12-04 04:29:44"
    },
    {
        "colo": "Default",
        "ip": "2606:4700:90c2:91db:bc72:fc88:aa37:a399",
        "latency": 22,
        "line": "CT",
        "loss": 0,
        "node": "WEBH",
        "speed": 309,
        "time": "2024-12-04 04:25:03"
    },
    {
        "colo": "Default",
        "ip": "2606:4700:90c2:52ca:2c76:2238:22eb:789f",
        "latency": 22,
        "line": "CT",
        "loss": 0,
        "node": "WEBH",
        "speed": 309,
        "time": "2024-12-04 04:25:03"
    },
    {
        "colo": "Default",
        "ip": "2606:4700:27:bc74:a151:1a3a:ce46:6499",
        "latency": 14,
        "line": "CT",
        "loss": 0,
        "node": "WEBH",
        "speed": 308,
        "time": "2024-12-04 04:15:07"
    },
    {
        "colo": "Default",
        "ip": "2606:4700:90c2:77b2:ee9c:bdb0:cdf5:c52d",
        "latency": 20,
        "line": "CT",
        "loss": 0,
        "node": "WEBH",
        "speed": 307,
        "time": "2024-12-04 04:25:03"
    },
    {
        "colo": "Default",
        "ip": "2606:4700:90c2:5c47:84f8:d072:9bd5:eb76",
        "latency": 20,
        "line": "CT",
        "loss": 0,
        "node": "WEBH",
        "speed": 307,
        "time": "2024-12-04 04:25:03"
    },
    {
        "colo": "Default",
        "ip": "2606:4700:3:31bf:6960:5e73:eb73:5d53",
        "latency": 11,
        "line": "CU",
        "loss": 0,
        "node": "CBUS",
        "speed": 625,
        "time": "2024-12-04 04:29:44"
    },
    {
        "colo": "Default",
        "ip": "2606:4700:3:6a69:36ae:11ca:6fd9:c9e0",
        "latency": 11,
        "line": "CU",
        "loss": 0,
        "node": "CBUS",
        "speed": 537,
        "time": "2024-12-04 04:29:44"
    },
    {
        "colo": "Default",
        "ip": "2606:4700:4403:fe6e:37bc:d441:1afc:b63c",
        "latency": 11,
        "line": "CU",
        "loss": 0,
        "node": "CBUS",
        "speed": 531,
        "time": "2024-12-04 04:29:43"
    },
    {
        "colo": "Default",
        "ip": "2606:4700:3:7af9:42c3:c98b:9753:5ccc",
        "latency": 11,
        "line": "CU",
        "loss": 0,
        "node": "CBUS",
        "speed": 502,
        "time": "2024-12-04 04:29:43"
    },
    {
        "colo": "Default",
        "ip": "2606:4700:4403:6e6d:8711:de0:6e0c:b046",
        "latency": 11,
        "line": "CU",
        "loss": 0,
        "node": "CBUS",
        "speed": 386,
        "time": "2024-12-04 04:29:44"
    }
]