[
    {
        "colo": "Default",
        "ip": "2606:4700:8390:9dca:9320:8a67:d52a:e038",
        "latency": 3,
        "line": "CM",
        "loss": 0,
        "node": "NETCUP",
        "speed": 597,
        "time": "2025-08-20 00:49:52"
    },
    {
        "colo": "Default",
        "ip": "2606:4700:8390:ffdb:3851:4b30:936c:e15",
        "latency": 3,
        "line": "CM",
        "loss": 0,
        "node": "NETCUP",
        "speed": 556,
        "time": "2025-08-20 00:49:51"
    },
    {
        "colo": "Default",
        "ip": "2606:4700:91b4:36c4:963:f4d8:b14b:ebdd",
        "latency": 3,
        "line": "CM",
        "loss": 0,
        "node": "NETCUP",
        "speed": 379,
        "time": "2025-08-20 00:49:52"
    },
    {
        "colo": "Default",
        "ip": "2606:4700:8cab:bb66:7cb1:e660:ec9b:13ae",
        "latency": 3,
        "line": "CM",
        "loss": 0,
        "node": "NETCUP",
        "speed": 366,
        "time": "2025-08-20 00:49:51"
    },
    {
        "colo": "Default",
        "ip": "2606:4700:9a95:2be1:f6e8:c041:9681:ade5",
        "latency": 4,
        "line": "CM",
        "loss": 0,
        "node": "NETCUP",
        "speed": 336,
        "time": "2025-08-20 00:49:51"
    },
    {
        "colo": "Default",
        "ip": "2606:4700:8390:9dca:9320:8a67:d52a:e038",
        "latency": 3,
        "line": "CT",
        "loss": 0,
        "node": "NETCUP",
        "speed": 597,
        "time": "2025-08-20 00:49:52"
    },
    {
        "colo": "Default",
        "ip": "2606:4700:8390:ffdb:3851:4b30:936c:e15",
        "latency": 3,
        "line": "CT",
        "loss": 0,
        "node": "NETCUP",
        "speed": 556,
        "time": "2025-08-20 00:49:51"
    },
    {
        "colo": "Default",
        "ip": "2606:4700:91b4:36c4:963:f4d8:b14b:ebdd",
        "latency": 3,
        "line": "CT",
        "loss": 0,
        "node": "NETCUP",
        "speed": 379,
        "time": "2025-08-20 00:49:52"
    },
    {
        "colo": "Default",
        "ip": "2606:4700:8cab:bb66:7cb1:e660:ec9b:13ae",
        "latency": 3,
        "line": "CT",
        "loss": 0,
        "node": "NETCUP",
        "speed": 366,
        "time": "2025-08-20 00:49:51"
    },
    {
        "colo": "Default",
        "ip": "2606:4700:9a95:2be1:f6e8:c041:9681:ade5",
        "latency": 4,
        "line": "CT",
        "loss": 0,
        "node": "NETCUP",
        "speed": 336,
        "time": "2025-08-20 00:49:51"
    },
    {
        "colo": "Default",
        "ip": "2606:4700:8390:9dca:9320:8a67:d52a:e038",
        "latency": 3,
        "line": "CU",
        "loss": 0,
        "node": "NETCUP",
        "speed": 597,
        "time": "2025-08-20 00:49:52"
    },
    {
        "colo": "Default",
        "ip": "2606:4700:8390:ffdb:3851:4b30:936c:e15",
        "latency": 3,
        "line": "CU",
        "loss": 0,
        "node": "NETCUP",
        "speed": 556,
        "time": "2025-08-20 00:49:51"
    },
    {
        "colo": "Default",
        "ip": "2606:4700:91b4:36c4:963:f4d8:b14b:ebdd",
        "latency": 3,
        "line": "CU",
        "loss": 0,
        "node": "NETCUP",
        "speed": 379,
        "time": "2025-08-20 00:49:52"
    },
    {
        "colo": "Default",
        "ip": "2606:4700:8cab:bb66:7cb1:e660:ec9b:13ae",
        "latency": 3,
        "line": "CU",
        "loss": 0,
        "node": "NETCUP",
        "speed": 366,
        "time": "2025-08-20 00:49:51"
    },
    {
        "colo": "Default",
        "ip": "2606:4700:9a95:2be1:f6e8:c041:9681:ade5",
        "latency": 4,
        "line": "CU",
        "loss": 0,
        "node": "NETCUP",
        "speed": 336,
        "time": "2025-08-20 00:49:51"
    }
]