[
    {
        "colo": "Default",
        "ip": "2606:4700:9ae8:a1a2:9d4e:53f6:5558:2c0f",
        "latency": 7,
        "line": "CM",
        "loss": 0,
        "node": "NETCUP",
        "speed": 624,
        "time": "2025-06-30 06:27:08"
    },
    {
        "colo": "Default",
        "ip": "2606:4700:9ae8:f89d:af3:4cad:d2ff:bdfd",
        "latency": 6,
        "line": "CM",
        "loss": 0,
        "node": "NETCUP",
        "speed": 624,
        "time": "2025-06-30 06:27:07"
    },
    {
        "colo": "Default",
        "ip": "2606:4700:9ae5:8fdf:3f2b:b71b:c59:cb4",
        "latency": 4,
        "line": "CM",
        "loss": 0,
        "node": "NETCUP",
        "speed": 441,
        "time": "2025-06-30 06:27:07"
    },
    {
        "colo": "Default",
        "ip": "2606:4700:9aed:d793:6d2d:e840:eaea:eecc",
        "latency": 5,
        "line": "CM",
        "loss": 0,
        "node": "NETCUP",
        "speed": 428,
        "time": "2025-06-30 06:27:07"
    },
    {
        "colo": "Default",
        "ip": "2606:4700:4403:5dda:e87f:9824:d3bc:1d61",
        "latency": 5,
        "line": "CM",
        "loss": 0,
        "node": "NETCUP",
        "speed": 427,
        "time": "2025-06-30 06:27:07"
    },
    {
        "colo": "Default",
        "ip": "2606:4700:9ae8:a1a2:9d4e:53f6:5558:2c0f",
        "latency": 7,
        "line": "CT",
        "loss": 0,
        "node": "NETCUP",
        "speed": 624,
        "time": "2025-06-30 06:27:08"
    },
    {
        "colo": "Default",
        "ip": "2606:4700:9ae8:f89d:af3:4cad:d2ff:bdfd",
        "latency": 6,
        "line": "CT",
        "loss": 0,
        "node": "NETCUP",
        "speed": 624,
        "time": "2025-06-30 06:27:07"
    },
    {
        "colo": "Default",
        "ip": "2606:4700:9ae5:8fdf:3f2b:b71b:c59:cb4",
        "latency": 4,
        "line": "CT",
        "loss": 0,
        "node": "NETCUP",
        "speed": 441,
        "time": "2025-06-30 06:27:07"
    },
    {
        "colo": "Default",
        "ip": "2606:4700:9aed:d793:6d2d:e840:eaea:eecc",
        "latency": 5,
        "line": "CT",
        "loss": 0,
        "node": "NETCUP",
        "speed": 428,
        "time": "2025-06-30 06:27:07"
    },
    {
        "colo": "Default",
        "ip": "2606:4700:4403:5dda:e87f:9824:d3bc:1d61",
        "latency": 5,
        "line": "CT",
        "loss": 0,
        "node": "NETCUP",
        "speed": 427,
        "time": "2025-06-30 06:27:07"
    },
    {
        "colo": "Default",
        "ip": "2606:4700:9ae8:a1a2:9d4e:53f6:5558:2c0f",
        "latency": 7,
        "line": "CU",
        "loss": 0,
        "node": "NETCUP",
        "speed": 624,
        "time": "2025-06-30 06:27:08"
    },
    {
        "colo": "Default",
        "ip": "2606:4700:9ae8:f89d:af3:4cad:d2ff:bdfd",
        "latency": 6,
        "line": "CU",
        "loss": 0,
        "node": "NETCUP",
        "speed": 624,
        "time": "2025-06-30 06:27:07"
    },
    {
        "colo": "Default",
        "ip": "2606:4700:9ae5:8fdf:3f2b:b71b:c59:cb4",
        "latency": 4,
        "line": "CU",
        "loss": 0,
        "node": "NETCUP",
        "speed": 441,
        "time": "2025-06-30 06:27:07"
    },
    {
        "colo": "Default",
        "ip": "2606:4700:9aed:d793:6d2d:e840:eaea:eecc",
        "latency": 5,
        "line": "CU",
        "loss": 0,
        "node": "NETCUP",
        "speed": 428,
        "time": "2025-06-30 06:27:07"
    },
    {
        "colo": "Default",
        "ip": "2606:4700:4403:5dda:e87f:9824:d3bc:1d61",
        "latency": 5,
        "line": "CU",
        "loss": 0,
        "node": "NETCUP",
        "speed": 427,
        "time": "2025-06-30 06:27:07"
    }
]