[
    {
        "colo": "Default",
        "ip": "2606:4700:9a9a:462b:8c92:96aa:1c6:3ae5",
        "latency": 3,
        "line": "CM",
        "loss": 0,
        "node": "NETCUP",
        "speed": 595,
        "time": "2025-07-24 13:40:15"
    },
    {
        "colo": "Default",
        "ip": "2606:4700:9b0c:e2e:3a9d:66df:5b4b:22aa",
        "latency": 4,
        "line": "CM",
        "loss": 0,
        "node": "NETCUP",
        "speed": 515,
        "time": "2025-07-24 13:40:14"
    },
    {
        "colo": "Default",
        "ip": "2606:4700:3020:c4b9:dbd9:e438:f6c5:9d85",
        "latency": 4,
        "line": "CM",
        "loss": 0,
        "node": "NETCUP",
        "speed": 482,
        "time": "2025-07-24 13:40:14"
    },
    {
        "colo": "Default",
        "ip": "2606:4700:9ad6:1b08:4e9a:4732:7b29:d192",
        "latency": 3,
        "line": "CM",
        "loss": 0,
        "node": "NETCUP",
        "speed": 401,
        "time": "2025-07-24 13:40:14"
    },
    {
        "colo": "Default",
        "ip": "2606:4700:3020:f429:8901:d3f9:252d:941e",
        "latency": 3,
        "line": "CM",
        "loss": 0,
        "node": "NETCUP",
        "speed": 390,
        "time": "2025-07-24 13:40:15"
    },
    {
        "colo": "Default",
        "ip": "2606:4700:9a9a:462b:8c92:96aa:1c6:3ae5",
        "latency": 3,
        "line": "CT",
        "loss": 0,
        "node": "NETCUP",
        "speed": 595,
        "time": "2025-07-24 13:40:15"
    },
    {
        "colo": "Default",
        "ip": "2606:4700:9b0c:e2e:3a9d:66df:5b4b:22aa",
        "latency": 4,
        "line": "CT",
        "loss": 0,
        "node": "NETCUP",
        "speed": 515,
        "time": "2025-07-24 13:40:14"
    },
    {
        "colo": "Default",
        "ip": "2606:4700:3020:c4b9:dbd9:e438:f6c5:9d85",
        "latency": 4,
        "line": "CT",
        "loss": 0,
        "node": "NETCUP",
        "speed": 482,
        "time": "2025-07-24 13:40:14"
    },
    {
        "colo": "Default",
        "ip": "2606:4700:9ad6:1b08:4e9a:4732:7b29:d192",
        "latency": 3,
        "line": "CT",
        "loss": 0,
        "node": "NETCUP",
        "speed": 401,
        "time": "2025-07-24 13:40:14"
    },
    {
        "colo": "Default",
        "ip": "2606:4700:3020:f429:8901:d3f9:252d:941e",
        "latency": 3,
        "line": "CT",
        "loss": 0,
        "node": "NETCUP",
        "speed": 390,
        "time": "2025-07-24 13:40:15"
    },
    {
        "colo": "Default",
        "ip": "2606:4700:9a9a:462b:8c92:96aa:1c6:3ae5",
        "latency": 3,
        "line": "CU",
        "loss": 0,
        "node": "NETCUP",
        "speed": 595,
        "time": "2025-07-24 13:40:15"
    },
    {
        "colo": "Default",
        "ip": "2606:4700:9b0c:e2e:3a9d:66df:5b4b:22aa",
        "latency": 4,
        "line": "CU",
        "loss": 0,
        "node": "NETCUP",
        "speed": 515,
        "time": "2025-07-24 13:40:14"
    },
    {
        "colo": "Default",
        "ip": "2606:4700:3020:c4b9:dbd9:e438:f6c5:9d85",
        "latency": 4,
        "line": "CU",
        "loss": 0,
        "node": "NETCUP",
        "speed": 482,
        "time": "2025-07-24 13:40:14"
    },
    {
        "colo": "Default",
        "ip": "2606:4700:9ad6:1b08:4e9a:4732:7b29:d192",
        "latency": 3,
        "line": "CU",
        "loss": 0,
        "node": "NETCUP",
        "speed": 401,
        "time": "2025-07-24 13:40:14"
    },
    {
        "colo": "Default",
        "ip": "2606:4700:3020:f429:8901:d3f9:252d:941e",
        "latency": 3,
        "line": "CU",
        "loss": 0,
        "node": "NETCUP",
        "speed": 390,
        "time": "2025-07-24 13:40:15"
    }
]