[
    {
        "colo": "Default",
        "ip": "2606:4700:3006:ac52:d1cf:5c92:7c45:3c2c",
        "latency": 11,
        "line": "CM",
        "loss": 0,
        "node": "CBUS",
        "speed": 543,
        "time": "2024-10-31 04:54:31"
    },
    {
        "colo": "Default",
        "ip": "2606:4700:3006:b66a:69d4:5f6:76fd:d0bb",
        "latency": 11,
        "line": "CM",
        "loss": 0,
        "node": "CBUS",
        "speed": 519,
        "time": "2024-10-31 04:54:31"
    },
    {
        "colo": "Default",
        "ip": "2606:4700:3006:ccb4:47eb:9867:f05d:681d",
        "latency": 11,
        "line": "CM",
        "loss": 0,
        "node": "CBUS",
        "speed": 513,
        "time": "2024-10-31 04:54:31"
    },
    {
        "colo": "Default",
        "ip": "2606:4700:3006:6450:fd80:2e55:3484:a748",
        "latency": 11,
        "line": "CM",
        "loss": 0,
        "node": "CBUS",
        "speed": 509,
        "time": "2024-10-31 04:54:31"
    },
    {
        "colo": "Default",
        "ip": "2606:4700:3006:ad5:3924:8cca:7c96:bc5a",
        "latency": 11,
        "line": "CM",
        "loss": 0,
        "node": "CBUS",
        "speed": 335,
        "time": "2024-10-31 04:54:31"
    },
    {
        "colo": "Default",
        "ip": "2606:4700:9ad7:68e4:a61a:5d09:4559:9793",
        "latency": 24,
        "line": "CT",
        "loss": 0,
        "node": "WEBH",
        "speed": 309,
        "time": "2024-10-31 04:45:25"
    },
    {
        "colo": "Default",
        "ip": "2606:4700:9ad7:826f:ce3f:d99a:9814:860b",
        "latency": 25,
        "line": "CT",
        "loss": 0,
        "node": "WEBH",
        "speed": 308,
        "time": "2024-10-31 04:45:25"
    },
    {
        "colo": "Default",
        "ip": "2606:4700:9ad7:d416:888:8d79:b716:b34d",
        "latency": 25,
        "line": "CT",
        "loss": 0,
        "node": "WEBH",
        "speed": 307,
        "time": "2024-10-31 04:45:26"
    },
    {
        "colo": "Default",
        "ip": "2606:4700:9ad7:b112:c291:a5e4:59b8:7f4d",
        "latency": 24,
        "line": "CT",
        "loss": 0,
        "node": "WEBH",
        "speed": 307,
        "time": "2024-10-31 04:45:25"
    },
    {
        "colo": "Default",
        "ip": "2606:4700:9ad7:f6d5:e5d6:9899:d644:17e4",
        "latency": 20,
        "line": "CT",
        "loss": 0,
        "node": "WEBH",
        "speed": 307,
        "time": "2024-10-31 04:45:25"
    },
    {
        "colo": "Default",
        "ip": "2606:4700:3006:ac52:d1cf:5c92:7c45:3c2c",
        "latency": 11,
        "line": "CU",
        "loss": 0,
        "node": "CBUS",
        "speed": 543,
        "time": "2024-10-31 04:54:31"
    },
    {
        "colo": "Default",
        "ip": "2606:4700:3006:b66a:69d4:5f6:76fd:d0bb",
        "latency": 11,
        "line": "CU",
        "loss": 0,
        "node": "CBUS",
        "speed": 519,
        "time": "2024-10-31 04:54:31"
    },
    {
        "colo": "Default",
        "ip": "2606:4700:3006:ccb4:47eb:9867:f05d:681d",
        "latency": 11,
        "line": "CU",
        "loss": 0,
        "node": "CBUS",
        "speed": 513,
        "time": "2024-10-31 04:54:31"
    },
    {
        "colo": "Default",
        "ip": "2606:4700:3006:6450:fd80:2e55:3484:a748",
        "latency": 11,
        "line": "CU",
        "loss": 0,
        "node": "CBUS",
        "speed": 509,
        "time": "2024-10-31 04:54:31"
    },
    {
        "colo": "Default",
        "ip": "2606:4700:3006:ad5:3924:8cca:7c96:bc5a",
        "latency": 11,
        "line": "CU",
        "loss": 0,
        "node": "CBUS",
        "speed": 335,
        "time": "2024-10-31 04:54:31"
    }
]